[
     {
          "title": "Test Title",
          "text": "Test text"
     },
     {
          "title": "Test Title Next A",
          "text": "Text one"
     },
     {
          "title": "Test Title Next B",
          "text": "Text two"
     },
     {
          "title": "Test Tittle Next C",
          "text": "This is content of note C"
     },
     {
          "title": "Test Title Next D",
          "text": "Note D Content"
     },
     {
          "title": "Test Tittle Next E",
          "text": "This is content of Note E"
     }
]